{
    "acquisition_software": "pychron 19.6",
    "aliquot": 1,
    "analysis_type": "unknown",
    "analyst_name": "",
    "arar_mapping": {
        "Ar36": "Ar36",
        "Ar37": "Ar37",
        "Ar38": "Ar38",
        "Ar39": "Ar39",
        "Ar40": "Ar40"
    },
    "collection_version": "1.0:2.0",
    "comment": "H:8 Muscovite, 10.27 mg",
    "commit": "bfdd48e2569e289421e0e74fc96c644bcfa4a176",
    "conditionals": [
        {
            "analysis_types": [],
            "frequency": 10,
            "hash_id": 5942297891161105181,
            "level": 10,
            "location": "setupfiles/spectrometer/default_conditionals.yaml",
            "ntrips": 1,
            "start_count": 5,
            "teststr": "L2(CDD).deflection==3250"
        }
    ],
    "data_reduction_software": "pychron 19.6",
    "detectors": {
        "AX": {
            "deflection": 0.0,
            "gain": 0.01205
        },
        "H1": {
            "deflection": 0.0,
            "gain": 0.1045
        },
        "H2": {
            "deflection": 0.0,
            "gain": 1.0
        },
        "L1": {
            "deflection": 0.0,
            "gain": 0.9831
        },
        "L2(CDD)": {
            "deflection": 0.0,
            "gain": 0.0
        }
    },
    "environmental": {
        "lab_humiditys": [
            {
                "device": "EnvironmentalMonitor",
                "name": "Lab Hum.",
                "pub_date": "2020-01-10T02:22:22",
                "title": "iServer Hum.",
                "value": 18.7
            }
        ],
        "lab_pneumatics": [
            {
                "device": "AirPressure",
                "name": "Pressure",
                "pub_date": "2020-01-10T01:26:14",
                "title": "Building",
                "value": 100.6
            },
            {
                "device": "AirPressure2",
                "name": "Pressure2",
                "pub_date": "2020-01-09T23:11:11",
                "title": "Lab",
                "value": 87.8
            },
            {
                "device": "MicroBoneGaugeController",
                "name": "JanDecabinPressure",
                "pub_date": "2020-01-09T22:56:10",
                "title": "Jan Decabin",
                "value": 2.4
            }
        ],
        "lab_temperatures": [
            {
                "device": "EnvironmentalMonitor",
                "name": "Lab Temp.",
                "pub_date": "2020-01-09T23:43:26",
                "title": "iServer Temp.",
                "value": 71.0
            },
            {
                "device": "Chiller",
                "name": "Coolant Temp.",
                "pub_date": "2020-01-10T02:21:11",
                "title": "Coolant",
                "value": 15.9
            }
        ]
    },
    "experiment_queue_name": "LoadF0007",
    "experiment_type": "Ar/Ar",
    "extraction": "felix_furnace.py",
    "grainsize": "",
    "hops": "",
    "identifier": "67352",
    "increment": 25,
    "instrument_name": "",
    "intensity_scalar": 0.0,
    "irradiation": "NM-306",
    "irradiation_level": "H",
    "irradiation_position": 8,
    "isotopes": {
        "Ar36": {
            "detector": "L2(CDD)",
            "name": "Ar36",
            "serial_id": "00000"
        },
        "Ar37": {
            "detector": "L1",
            "name": "Ar37",
            "serial_id": "00000"
        },
        "Ar38": {
            "detector": "AX",
            "name": "Ar38",
            "serial_id": "00000"
        },
        "Ar39": {
            "detector": "H1",
            "name": "Ar39",
            "serial_id": "00000"
        },
        "Ar40": {
            "detector": "H2",
            "name": "Ar40",
            "serial_id": "00000"
        }
    },
    "laboratory": "",
    "latitude": 0.0,
    "lithology": null,
    "lithology_class": null,
    "lithology_group": null,
    "lithology_type": null,
    "longitude": 0.0,
    "mass_spectrometer": "felix",
    "material": "Muscovite",
    "measurement": "felix_analysis340_60_CDD_center.py",
    "post_equilibration": "felix_pump_extraction_line.py",
    "post_measurement": "felix_pump_ms.py",
    "principal_investigator": "Wells, M",
    "project": "Wells01228",
    "queue_conditionals_name": "",
    "repository_identifier": "Wells01228",
    "rlocation": "",
    "sample": "WB19TM-44",
    "source": {
        "emission": 797.054,
        "trap": 249.054
    },
    "spec_sha": "9839df14193423094cb9c2b3f03e4ee25da166e9",
    "timestamp": "2020-01-10T02:29:43.252252",
    "tripped_conditional": null,
    "unit": null,
    "username": "",
    "uuid": "620c96cf-1983-4b56-a325-5d5fee47ac00",
    "whiff_result": null
}