{
    "Ar36": {
        "error": 0.001049118772872569,
        "error_type": "SEM",
        "filter_outliers_dict": {
            "filter_outliers": true,
            "iterations": 2,
            "std_devs": 2
        },
        "fit": "Parabolic",
        "value": 0.16158652239777133
    },
    "Ar37": {
        "error": 0.014090459525360593,
        "error_type": "SEM",
        "filter_outliers_dict": {
            "filter_outliers": true,
            "iterations": 2,
            "std_devs": 2
        },
        "fit": "linear",
        "value": 0.5207051659952024
    },
    "Ar38": {
        "error": 0.0051928062677020995,
        "error_type": "SEM",
        "filter_outliers_dict": {
            "filter_outliers": true,
            "iterations": 2,
            "std_devs": 2
        },
        "fit": "linear",
        "value": 0.6654885093303686
    },
    "Ar39": {
        "error": 0.016770561860370497,
        "error_type": "SEM",
        "filter_outliers_dict": {
            "filter_outliers": true,
            "iterations": 2,
            "std_devs": 2
        },
        "fit": "Parabolic",
        "value": 42.21358442421076
    },
    "Ar40": {
        "error": 0.050057529131378946,
        "error_type": "SEM",
        "filter_outliers_dict": {
            "filter_outliers": true,
            "iterations": 2,
            "std_devs": 2
        },
        "fit": "Parabolic",
        "value": 414.1545339319588
    }
}